MANIFEST.in
README.md
setup.py
apps/__init__.py
apps/admin.py
apps/cimm.py
apps/config.py
apps/context.py
apps/cprdata.py
apps/excel.py
apps/fillpw.py
apps/imm_api.py
apps/login.py
apps/sysdict.py
imm_client.egg-info/PKG-INFO
imm_client.egg-info/SOURCES.txt
imm_client.egg-info/dependency_links.txt
imm_client.egg-info/entry_points.txt
imm_client.egg-info/top_level.txt
pdfform/__init__.py
pdfform/application_form.py
pdfform/config_mac.py
pdfform/config_win.py
pdfform/context.py
pdfform/fb5476.py
pdfform/form_controls_mac.py
pdfform/form_controls_win.py
pdfform/jsonmaker.py
pdfform/pdfs/0008.pdf
pdfform/pdfs/0104.pdf
pdfform/pdfs/1294.pdf
pdfform/pdfs/1295.pdf
pdfform/pdfs/5257.pdf
pdfform/pdfs/5257b_1.pdf
pdfform/pdfs/5406.pdf
pdfform/pdfs/5476.pdf
pdfform/pdfs/5562.pdf
pdfform/pdfs/5645.pdf
pdfform/pdfs/5669.pdf
pdfform/pdfs/5708.pdf
pdfform/pdfs/5709.pdf
pdfform/pdfs/5710.pdf
pdfform/pdfs/bc_edf.pdf
pdfform/pdfs/bc_rep_ee.pdf
pdfform/pdfs/bc_rep_er.pdf
source/__init__.py
source/comment.py
source/excel.py
source/excelwriter.py
source/formatdefinition.py
source/infosheet.py
source/tablesheet.py
source/validation.py
system/__init__.py
system/config.py
system/models.py
utils/__init__.py
utils/areas.py
utils/canada.py
utils/files.py
utils/language.py
utils/pdf.py
utils/setbase.py
utils/utils.py
utils/word.py